flowerhub_portal_api_client/__init__.py
flowerhub_portal_api_client/async_client.py
flowerhub_portal_api_client/exceptions.py
flowerhub_portal_api_client/parsers.py
flowerhub_portal_api_client/types.py
flowerhub_portal_api_client-1.0.0.dist-info/licenses/LICENSE
flowerhub_portal_api_client-1.0.0.dist-info/METADATA
flowerhub_portal_api_client-1.0.0.dist-info/WHEEL
flowerhub_portal_api_client-1.0.0.dist-info/top_level.txt
flowerhub_portal_api_client-1.0.0.dist-info/RECORD
