Metadata-Version: 2.4
Name: flowerhub-portal-api-client
Version: 1.0.0
Summary: Lightweight Flowerhub portal client (synchronous and async)
Author-email: Michael Pihlblad <michael.pihlblad@bahnhof.se>
License-Expression: Apache-2.0
Requires-Python: >=3.10
License-File: LICENSE
Requires-Dist: requests>=2.31
Requires-Dist: pyjwt>=2.8
Provides-Extra: async
Requires-Dist: aiohttp>=3.8; extra == "async"
Dynamic: license-file
